scripnester/__init__.py
scripnester/rigstral.py
scripnester/scripstral.py
scripnester-1.0.0.0.dist-info/METADATA
scripnester-1.0.0.0.dist-info/WHEEL
scripnester-1.0.0.0.dist-info/licenses/LICENSE.txt
scripnester-1.0.0.0.dist-info/RECORD
